exifparser/__init__.py
exifparser/exif.py
exifparser_BootingBarnacles-0.0.1.dist-info/LICENSE
exifparser_BootingBarnacles-0.0.1.dist-info/METADATA
exifparser_BootingBarnacles-0.0.1.dist-info/WHEEL
exifparser_BootingBarnacles-0.0.1.dist-info/top_level.txt
exifparser_BootingBarnacles-0.0.1.dist-info/RECORD
